mithen/__init__.py
mithen/mithen.py
mithen-0.0.5.dist-info/LICENSE
mithen-0.0.5.dist-info/METADATA
mithen-0.0.5.dist-info/WHEEL
mithen-0.0.5.dist-info/top_level.txt
mithen-0.0.5.dist-info/RECORD
