Metadata-Version: 2.1
Name: mithen
Version: 0.0.5
Summary: Krypton için geliştirilmiş bir eklenti paketi.
Home-page: https://github.com/beratcmn/mithen
Author: Berat Çimen
Author-email: beratcmn@gmail.com
License: UNKNOWN
Project-URL: Bug Tracker, https://github.com/beratcmn/mithen/issues
Platform: UNKNOWN
Classifier: Programming Language :: Python :: 3
Classifier: License :: OSI Approved :: MIT License
Classifier: Operating System :: OS Independent
Requires-Python: >=3.6
License-File: LICENSE
